docs/source/conf.py
kronolapse/ModKronoLapse.py
kronolapse/ModMostrarImagen.py
kronolapse/ModTiempo.py
kronolapse/__init__.py
kronolapse/__main__.py
kronolapse-0.2.0a1.dist-info/licenses/AUTHORS
kronolapse-0.2.0a1.dist-info/licenses/LICENSE
tests/ModGenFiles.py
tests/__init__.py
tests/gen_demo_files.py
tests/test_module_kronolapse.py
tests/test_script_kronolapse.py
tests/test_version.py
venv/bin/activate_this.py
kronolapse-0.2.0a1.dist-info/METADATA
kronolapse-0.2.0a1.dist-info/WHEEL
kronolapse-0.2.0a1.dist-info/entry_points.txt
kronolapse-0.2.0a1.dist-info/top_level.txt
kronolapse-0.2.0a1.dist-info/RECORD
