Metadata-Version: 2.4
Name: kronolapse
Version: 0.2.0a1
Summary: Management the display of images on a monitor according to a schedule and time intervals
Author-email: Miguel Molina <mmolina.unphysics@gmail.com>
License-Expression: GPL-3.0-or-later
Project-URL: Homepage, https://github.com/mikemolina/kronolapse
Project-URL: Repository, https://github.com/mikemolina/kronolapse.git
Project-URL: Issues, https://github.com/mikemolina/kronolapse/issues
Project-URL: Changelog, https://github.com/mikemolina/kronolapse/blob/main/ChangeLog.md
Keywords: schedule,presentation slide,digital signage,digital displays
Classifier: Development Status :: 3 - Alpha
Classifier: Environment :: Console
Classifier: Intended Audience :: Education
Classifier: Intended Audience :: Information Technology
Classifier: Intended Audience :: Telecommunications Industry
Classifier: Natural Language :: Spanish
Classifier: Operating System :: OS Independent
Classifier: Programming Language :: Python :: 3
Classifier: Topic :: Communications
Classifier: Topic :: Multimedia :: Graphics :: Presentation
Classifier: Topic :: Office/Business :: Scheduling
Requires-Python: >=3.12
License-File: LICENSE
License-File: AUTHORS
Requires-Dist: numpy
Requires-Dist: opencv-python
Requires-Dist: screeninfo
Provides-Extra: dev
Requires-Dist: build; extra == "dev"
Requires-Dist: setuptools; extra == "dev"
Requires-Dist: wheel; extra == "dev"
Requires-Dist: pytest; extra == "dev"
Requires-Dist: pillow; extra == "dev"
Provides-Extra: doc
Requires-Dist: sphinx>=7.0.0; extra == "doc"
Requires-Dist: sphinx-pyproject; extra == "doc"
Requires-Dist: sphinx-rtd-theme; extra == "doc"
Requires-Dist: sphinx-breeze-theme; extra == "doc"
Requires-Dist: sphinx-copybutton; extra == "doc"
Requires-Dist: myst-parser; extra == "doc"
Dynamic: license-file
